recitale/__init__.py
recitale/audio.py
recitale/autogen.py
recitale/cache.py
recitale/image.py
recitale/recitale.py
recitale/utils.py
recitale/video.py
recitale/themes/exposure/static/css/baguetteBox.min.css
recitale/themes/exposure/static/css/encrypt.css
recitale/themes/exposure/static/css/fonts.css
recitale/themes/exposure/static/css/mediaelementplayer.css
recitale/themes/exposure/static/css/mejs-controls.svg
recitale/themes/exposure/static/css/panorama_viewer.css
recitale/themes/exposure/static/css/style-page.css
recitale/themes/exposure/static/css/style.css
recitale/themes/exposure/static/fonts/crimsontext-bold-webfont.eot
recitale/themes/exposure/static/fonts/crimsontext-bold-webfont.svg
recitale/themes/exposure/static/fonts/crimsontext-bold-webfont.ttf
recitale/themes/exposure/static/fonts/crimsontext-bold-webfont.woff
recitale/themes/exposure/static/fonts/crimsontext-bold-webfont.woff2
recitale/themes/exposure/static/fonts/crimsontext-bolditalic-webfont.eot
recitale/themes/exposure/static/fonts/crimsontext-bolditalic-webfont.svg
recitale/themes/exposure/static/fonts/crimsontext-bolditalic-webfont.ttf
recitale/themes/exposure/static/fonts/crimsontext-bolditalic-webfont.woff
recitale/themes/exposure/static/fonts/crimsontext-bolditalic-webfont.woff2
recitale/themes/exposure/static/fonts/crimsontext-italic-webfont.eot
recitale/themes/exposure/static/fonts/crimsontext-italic-webfont.svg
recitale/themes/exposure/static/fonts/crimsontext-italic-webfont.ttf
recitale/themes/exposure/static/fonts/crimsontext-italic-webfont.woff
recitale/themes/exposure/static/fonts/crimsontext-italic-webfont.woff2
recitale/themes/exposure/static/fonts/crimsontext-regular-webfont.eot
recitale/themes/exposure/static/fonts/crimsontext-regular-webfont.svg
recitale/themes/exposure/static/fonts/crimsontext-regular-webfont.ttf
recitale/themes/exposure/static/fonts/crimsontext-regular-webfont.woff
recitale/themes/exposure/static/fonts/crimsontext-regular-webfont.woff2
recitale-2.0.0a6.dist-info/LICENSE
recitale-2.0.0a6.dist-info/METADATA
recitale-2.0.0a6.dist-info/WHEEL
recitale-2.0.0a6.dist-info/entry_points.txt
recitale-2.0.0a6.dist-info/top_level.txt
recitale-2.0.0a6.dist-info/RECORD
