Metadata-Version: 2.1
Name: recitale
Version: 2.0.0a6
Summary: A static website generator that allows you to tell a story with your pictures
Home-page: https://github.com/recitale/recitale
Author: Quentin Schulz
Author-email: foss+recitale@0leil.net
License: GPL-3.0-or-later
Classifier: Development Status :: 3 - Alpha
Classifier: Environment :: Console
Classifier: Intended Audience :: End Users/Desktop
Classifier: License :: OSI Approved :: GNU General Public License v3 or later (GPLv3+)
Classifier: Programming Language :: Python :: 3 :: Only
Requires-Python: >=3.0
License-File: LICENSE
Requires-Dist: Babel
Requires-Dist: future
Requires-Dist: imagesize
Requires-Dist: jinja2 >=2.9
Requires-Dist: pillow >=6
Requires-Dist: pycryptodomex
Requires-Dist: ruamel.yaml <0.18.0
Requires-Dist: tqdm
Provides-Extra: tests
Requires-Dist: pytest ; extra == 'tests'
Requires-Dist: pytest-cov ; extra == 'tests'
